dfmt/__init__.py
dfmt-1.2.0.dist-info/entry_points.txt
dfmt-1.2.0.dist-info/WHEEL
dfmt-1.2.0.dist-info/METADATA
dfmt-1.2.0.dist-info/RECORD
