Metadata-Version: 2.1
Name: dfmt
Version: 1.2.0
Summary: 
Home-page: https://github.com/dmerejkowsky/dfmt
License: BSD-3-Clause
Author: Dimitri Merejkowsky
Author-email: d.merej@gmail.com
Requires-Python: >=3.7,<4.0
Classifier: License :: OSI Approved :: BSD License
Classifier: Programming Language :: Python :: 3
Classifier: Programming Language :: Python :: 3.7
Classifier: Programming Language :: Python :: 3.8
Project-URL: Repository, https://github.com/dmerejkowsky/dfmt
